{
  "name": "bat",
  "extends": "../artbook.json",
  "meaning": "hostile",
  "entity": "the-shadow",
  "legend": {
    "S": "shadow",
    "s": "shadow_hi",
    "r": "cloak",
    "X": "gold",
    "e": "outline",
    "t": "shadow"
  },
  "layers": [
    {
      "name": "bat",
      "pixels": [
        "....................",
        "....................",
        "...S............S...",
        "..SSS..ssss...SSS...",
        ".SSSSSsSSSSssSSSSS..",
        "SSSSSSSSrrSSSSSSSSS.",
        "SSSSSSSrXrSrSSSSSSS.",
        ".SSSSSSSSSSSSSSSSS..",
        "..SSS.eSSSSse.SSS...",
        "...S...SSSSS...S....",
        "........SSS.........",
        ".........tt.........",
        "....................",
        "....................",
        "....................",
        "....................",
        "....................",
        "....................",
        "....................",
        "...................."
      ]
    }
  ]
}